model_drift_detector/__init__.py
model_drift_detector/detector.py
model_drift_detector/types.py
model_drift_detector-0.1.0.dist-info/METADATA
model_drift_detector-0.1.0.dist-info/WHEEL
model_drift_detector-0.1.0.dist-info/licenses/LICENSE
model_drift_detector-0.1.0.dist-info/RECORD
