Metadata-Version: 2.4
Name: model-drift-detector
Version: 0.1.0
Summary: Production monitoring for ML model drift - detect data drift, concept drift, and performance degradation
Project-URL: Homepage, https://github.com/pranaym/model-drift-detector
Project-URL: Documentation, https://github.com/pranaym/model-drift-detector#readme
Project-URL: Repository, https://github.com/pranaym/model-drift-detector
Project-URL: Issues, https://github.com/pranaym/model-drift-detector/issues
Author-email: Pranay M <pranay@example.com>
License-Expression: MIT
License-File: LICENSE
Keywords: concept-drift,data-drift,drift-detection,machine-learning,mlops,model-monitoring,production-ml,statistical-testing
Classifier: Development Status :: 4 - Beta
Classifier: Intended Audience :: Developers
Classifier: Intended Audience :: Science/Research
Classifier: License :: OSI Approved :: MIT License
Classifier: Operating System :: OS Independent
Classifier: Programming Language :: Python :: 3
Classifier: Programming Language :: Python :: 3.8
Classifier: Programming Language :: Python :: 3.9
Classifier: Programming Language :: Python :: 3.10
Classifier: Programming Language :: Python :: 3.11
Classifier: Programming Language :: Python :: 3.12
Classifier: Topic :: Scientific/Engineering :: Artificial Intelligence
Classifier: Typing :: Typed
Requires-Python: >=3.8
Provides-Extra: dev
Requires-Dist: black>=23.0.0; extra == 'dev'
Requires-Dist: mypy>=1.0.0; extra == 'dev'
Requires-Dist: pytest-cov>=4.0.0; extra == 'dev'
Requires-Dist: pytest>=7.0.0; extra == 'dev'
Requires-Dist: ruff>=0.1.0; extra == 'dev'
Provides-Extra: full
Requires-Dist: matplotlib>=3.5.0; extra == 'full'
Requires-Dist: numpy>=1.20.0; extra == 'full'
Requires-Dist: pandas>=1.3.0; extra == 'full'
Requires-Dist: scipy>=1.7.0; extra == 'full'
Provides-Extra: ml
Requires-Dist: numpy>=1.20.0; extra == 'ml'
Requires-Dist: pandas>=1.3.0; extra == 'ml'
Requires-Dist: scipy>=1.7.0; extra == 'ml'
Provides-Extra: scipy
Requires-Dist: scipy>=1.7.0; extra == 'scipy'
